examples/BasicThunderBorgControl.py
examples/RemoteControlTest.py
examples/ThunderRemoteBasic.py
examples/ThunderRemoteMadness.py
examples/ThunderrRemoteAny.py
examples/__init__.py
setup/PatchLibrary.py
setup/__init__.py
thunder_remote/AlarmClock.py
thunder_remote/ControllerMapping.py
thunder_remote/DebugLevel.py
thunder_remote/RemoteControl.py
thunder_remote/RemoteControlEvents.py
thunder_remote/__init__.py
thunder_remote/__main__.py
thunder_remote/profiles/default.csv
thunder_remote/profiles/madness.csv
thunder_remote-0.6.2.dist-info/LICENSE-3RD-PARTY.md
thunder_remote-0.6.2.dist-info/LICENSE.md
thunder_remote-0.6.2.dist-info/METADATA
thunder_remote-0.6.2.dist-info/WHEEL
thunder_remote-0.6.2.dist-info/top_level.txt
thunder_remote-0.6.2.dist-info/RECORD
