Metadata-Version: 2.1
Name: thunder-remote
Version: 0.6.2
Summary: A modified version of the 'pyController' package for usage with a ThunderBorg
Home-page: https://github.com/Schrotty/thunder-remote
Author: Schrotty
Author-email: rubenmaurer@live.de
License: MIT
Keywords: thunder-borg borg remote-control remote rc
Platform: UNKNOWN
Classifier: Development Status :: 4 - Beta
Classifier: Programming Language :: Python :: 2.7
Classifier: License :: OSI Approved :: MIT License
Classifier: Operating System :: OS Independent
Classifier: Intended Audience :: Developers
Classifier: Topic :: Software Development :: Libraries
Requires-Dist: inputs
Requires-Dist: events
Requires-Dist: enum34
